novelai/__init__.py
novelai/__main__.py
novelai/client.py
novelai/constant.py
novelai/exceptions.py
novelai/utils.py
novelai/types/__init__.py
novelai/types/hostinstance.py
novelai/types/image.py
novelai/types/metadata.py
novelai/types/user.py
novelai_legacy-1.0.0rc1.dist-info/LICENSE
novelai_legacy-1.0.0rc1.dist-info/METADATA
novelai_legacy-1.0.0rc1.dist-info/WHEEL
novelai_legacy-1.0.0rc1.dist-info/top_level.txt
novelai_legacy-1.0.0rc1.dist-info/RECORD
